{
    "on-table(milk-carton,wood-table)": 0.27914670468696084,
    "on-table(milk-carton,black-table)": 0.2579735761659852,
    "on-table(milk-carton,white-table)": 0.6478793229131649,
    "on-table(lemon,wood-table)": 0.01627990543784108,
    "on-table(lemon,black-table)": 0.6011588104690114,
    "on-table(lemon,white-table)": 0.026103657964919574,
    "on-table(green-bottle,wood-table)": 0.7872625458985567,
    "on-table(green-bottle,black-table)": 0.1685756108403401,
    "on-table(green-bottle,white-table)": 0.003295444388868418,
    "on-table(loaf-of-bread,wood-table)": 0.05480010656174272,
    "on-table(loaf-of-bread,black-table)": 0.22608486138051376,
    "on-table(loaf-of-bread,white-table)": 0.10443816534340537,
    "on-table(red-box-of-cereal,wood-table)": 0.3448547096243904,
    "on-table(red-box-of-cereal,black-table)": 0.9043056815862656,
    "on-table(red-box-of-cereal,white-table)": 0.014570728948456235,
    "on-table(red-can-of-soda,wood-table)": 0.3124898567039054,
    "on-table(red-can-of-soda,black-table)": 0.7433098430434862,
    "on-table(red-can-of-soda,white-table)": 0.015463638299479499,
    "robot-gripper-empty()": 0.8924234410127004,
    "robot-gripping(milk-carton)": 0.2197380910317103,
    "robot-gripping(lemon)": 0.06526850288112958,
    "robot-gripping(green-bottle)": 0.07411382296898712,
    "robot-gripping(loaf-of-bread)": 0.10481525398790836,
    "robot-gripping(red-box-of-cereal)": 0.20636266376823187,
    "robot-gripping(red-can-of-soda)": 0.5722905763735374
}