{
    "on-table(milk-carton,wood-table)": 0.8637374639511108,
    "on-table(milk-carton,black-table)": 0.18082212530619776,
    "on-table(milk-carton,white-table)": 0.1721597715441021,
    "on-table(lemon,wood-table)": 0.1663573035305793,
    "on-table(lemon,black-table)": 0.8353455706189076,
    "on-table(lemon,white-table)": 0.013811217827954655,
    "on-table(green-bottle,wood-table)": 0.33309625468731,
    "on-table(green-bottle,black-table)": 0.997215986251831,
    "on-table(green-bottle,white-table)": 0.004015410391275509,
    "on-table(loaf-of-bread,wood-table)": 0.26205680270989734,
    "on-table(loaf-of-bread,black-table)": 0.0034524684112208583,
    "on-table(loaf-of-bread,white-table)": 0.5667685475394441,
    "on-table(red-box-of-cereal,wood-table)": 0.9554884433746338,
    "on-table(red-box-of-cereal,black-table)": 0.31747775749295215,
    "on-table(red-box-of-cereal,white-table)": 0.061928669884158204,
    "on-table(red-can-of-soda,wood-table)": 0.9853462974230448,
    "on-table(red-can-of-soda,black-table)": 0.32907719795290785,
    "on-table(red-can-of-soda,white-table)": 0.053362917432915914,
    "robot-gripper-empty()": 0.867838054895401,
    "robot-gripping(milk-carton)": 0.214945358534654,
    "robot-gripping(lemon)": 0.03059989116930713,
    "robot-gripping(green-bottle)": 0.09244767085571463,
    "robot-gripping(loaf-of-bread)": 0.10248820204287767,
    "robot-gripping(red-box-of-cereal)": 0.10875579691492021,
    "robot-gripping(red-can-of-soda)": 0.17541521702272198
}