{
    "on-table(milk-carton,wood-table)": 0.2730780343990773,
    "on-table(milk-carton,black-table)": 0.6897670676310858,
    "on-table(milk-carton,white-table)": 0.022011715331852127,
    "on-table(lemon,wood-table)": 0.1725972491161277,
    "on-table(lemon,black-table)": 0.010521368958810248,
    "on-table(lemon,white-table)": 0.8349930917223295,
    "on-table(green-bottle,wood-table)": 0.16489168126766648,
    "on-table(green-bottle,black-table)": 0.00043170161393391027,
    "on-table(green-bottle,white-table)": 0.8338841477331395,
    "on-table(loaf-of-bread,wood-table)": 0.4589340017409995,
    "on-table(loaf-of-bread,black-table)": 0.4463575587918361,
    "on-table(loaf-of-bread,white-table)": 0.11066635918299046,
    "on-table(red-box-of-cereal,wood-table)": 0.49112304754089564,
    "on-table(red-box-of-cereal,black-table)": 0.5552753708616365,
    "on-table(red-box-of-cereal,white-table)": 0.003338896933807215,
    "on-table(red-can-of-soda,wood-table)": 0.7472634801330665,
    "on-table(red-can-of-soda,black-table)": 0.5010578197601111,
    "on-table(red-can-of-soda,white-table)": 0.0004936527441259386,
    "robot-gripper-empty()": 0.8760389139254888,
    "robot-gripping(milk-carton)": 0.13041134799520174,
    "robot-gripping(lemon)": 0.0630035496627291,
    "robot-gripping(green-bottle)": 0.009464688249863684,
    "robot-gripping(loaf-of-bread)": 0.13766963966190815,
    "robot-gripping(red-box-of-cereal)": 0.031167310429736972,
    "robot-gripping(red-can-of-soda)": 0.18010267103090882
}