{
    "on-table(milk-carton,wood-table)": 0.2807961852910618,
    "on-table(milk-carton,black-table)": 0.1889530653837331,
    "on-table(milk-carton,white-table)": 0.03657156599122876,
    "on-table(lemon,wood-table)": 0.24543026820902014,
    "on-table(lemon,black-table)": 0.0013078066409661915,
    "on-table(lemon,white-table)": 0.9802388846874237,
    "on-table(green-bottle,wood-table)": 0.16873416947297906,
    "on-table(green-bottle,black-table)": 0.00177518335347789,
    "on-table(green-bottle,white-table)": 0.8360444055870175,
    "on-table(loaf-of-bread,wood-table)": 0.13071038802930465,
    "on-table(loaf-of-bread,black-table)": 0.015483014603281239,
    "on-table(loaf-of-bread,white-table)": 0.078295943687408,
    "on-table(red-box-of-cereal,wood-table)": 0.3534057693711172,
    "on-table(red-box-of-cereal,black-table)": 0.33129708755222964,
    "on-table(red-box-of-cereal,white-table)": 0.013883784506712496,
    "on-table(red-can-of-soda,wood-table)": 0.9958455264568329,
    "on-table(red-can-of-soda,black-table)": 0.33307257951656766,
    "on-table(red-can-of-soda,white-table)": 0.005258578506224391,
    "robot-gripper-empty()": 0.9813752174377441,
    "robot-gripping(milk-carton)": 0.2591183011730512,
    "robot-gripping(lemon)": 0.048543363731975354,
    "robot-gripping(green-bottle)": 0.01539440693644186,
    "robot-gripping(loaf-of-bread)": 0.05872121794770161,
    "robot-gripping(red-box-of-cereal)": 0.02299075247719884,
    "robot-gripping(red-can-of-soda)": 0.060762019672741495
}