{
    "on-table(milk-carton,wood-table)": 0.5493424510738502,
    "on-table(milk-carton,black-table)": 0.4086937637378772,
    "on-table(milk-carton,white-table)": 0.18987582203408238,
    "on-table(lemon,wood-table)": 0.011095595507261654,
    "on-table(lemon,black-table)": 0.11752644874892819,
    "on-table(lemon,white-table)": 0.319842726981733,
    "on-table(green-bottle,wood-table)": 0.0029010767951452485,
    "on-table(green-bottle,black-table)": 0.271927172250192,
    "on-table(green-bottle,white-table)": 0.08593584630398254,
    "on-table(loaf-of-bread,wood-table)": 0.4619215761971039,
    "on-table(loaf-of-bread,black-table)": 0.004876370590560934,
    "on-table(loaf-of-bread,white-table)": 0.5177264811548715,
    "on-table(red-box-of-cereal,wood-table)": 0.8388107226540645,
    "on-table(red-box-of-cereal,black-table)": 0.2986721766143698,
    "on-table(red-box-of-cereal,white-table)": 0.011688722560999546,
    "on-table(red-can-of-soda,wood-table)": 0.4402494854487789,
    "on-table(red-can-of-soda,black-table)": 0.610429227973024,
    "on-table(red-can-of-soda,white-table)": 0.00573055460517935,
    "robot-gripper-empty()": 0.8292728314797083,
    "robot-gripping(milk-carton)": 0.2693736758083105,
    "robot-gripping(lemon)": 0.14988916087895632,
    "robot-gripping(green-bottle)": 0.2073949531574423,
    "robot-gripping(loaf-of-bread)": 0.1874201906224092,
    "robot-gripping(red-box-of-cereal)": 0.17649906018050388,
    "robot-gripping(red-can-of-soda)": 0.22820658283308148
}