{
    "on-table(milk-carton,wood-table)": 0.2816129356312255,
    "on-table(milk-carton,black-table)": 0.013612278601309905,
    "on-table(milk-carton,white-table)": 0.6845025472963849,
    "on-table(lemon,wood-table)": 0.07694798006559722,
    "on-table(lemon,black-table)": 0.054591854995427035,
    "on-table(lemon,white-table)": 0.019769162259763107,
    "on-table(green-bottle,wood-table)": 0.004607641957894278,
    "on-table(green-bottle,black-table)": 0.004406791910393319,
    "on-table(green-bottle,white-table)": 0.00024894890945385367,
    "on-table(loaf-of-bread,wood-table)": 0.578604307025671,
    "on-table(loaf-of-bread,black-table)": 0.05414317678999699,
    "on-table(loaf-of-bread,white-table)": 0.09028989813911419,
    "on-table(red-box-of-cereal,wood-table)": 0.20846846686617937,
    "on-table(red-box-of-cereal,black-table)": 0.004838045038316825,
    "on-table(red-box-of-cereal,white-table)": 0.838204987347126,
    "on-table(red-can-of-soda,wood-table)": 0.18426608707522973,
    "on-table(red-can-of-soda,black-table)": 0.0015372318212030223,
    "on-table(red-can-of-soda,white-table)": 0.8337866376775006,
    "robot-gripper-empty()": 0.7349622522791227,
    "robot-gripping(milk-carton)": 0.2622983753681183,
    "robot-gripping(lemon)": 0.04395959308991829,
    "robot-gripping(green-bottle)": 0.020593334804289043,
    "robot-gripping(loaf-of-bread)": 0.07166783232241869,
    "robot-gripping(red-box-of-cereal)": 0.21299153364573917,
    "robot-gripping(red-can-of-soda)": 0.3480330544213454
}