{
    "on-table(milk-carton,wood-table)": 0.34423262625932693,
    "on-table(milk-carton,black-table)": 0.0527479643545424,
    "on-table(milk-carton,white-table)": 0.030827537450628977,
    "on-table(lemon,wood-table)": 0.16838753824898353,
    "on-table(lemon,black-table)": 0.6676827325330427,
    "on-table(lemon,white-table)": 0.0032309964412888803,
    "on-table(green-bottle,wood-table)": 0.16925340094894636,
    "on-table(green-bottle,black-table)": 0.0034678832451694084,
    "on-table(green-bottle,white-table)": 0.8364709963401159,
    "on-table(loaf-of-bread,wood-table)": 0.3323163700600465,
    "on-table(loaf-of-bread,black-table)": 0.1048156634157446,
    "on-table(loaf-of-bread,white-table)": 0.018202726714662276,
    "on-table(red-box-of-cereal,wood-table)": 0.2927361637751649,
    "on-table(red-box-of-cereal,black-table)": 0.0019106606268906035,
    "on-table(red-box-of-cereal,white-table)": 0.0043249721123477984,
    "on-table(red-can-of-soda,wood-table)": 0.2440929500492833,
    "on-table(red-can-of-soda,black-table)": 0.0006559325108052386,
    "on-table(red-can-of-soda,white-table)": 0.0006309189921012148,
    "robot-gripper-empty()": 0.965679277976354,
    "robot-gripping(milk-carton)": 0.1697914575537046,
    "robot-gripping(lemon)": 0.023850238571564358,
    "robot-gripping(green-bottle)": 0.010956504944867143,
    "robot-gripping(loaf-of-bread)": 0.060760415624827147,
    "robot-gripping(red-box-of-cereal)": 0.011446971543288479,
    "robot-gripping(red-can-of-soda)": 0.040764716221019626
}