{
    "on-table(milk-carton,wood-table)": 0.041326764160961225,
    "on-table(milk-carton,black-table)": 0.7926000934094191,
    "on-table(milk-carton,white-table)": 0.007308680944940231,
    "on-table(lemon,wood-table)": 0.030403718434778664,
    "on-table(lemon,black-table)": 0.6708605269280573,
    "on-table(lemon,white-table)": 0.004946945101134285,
    "on-table(green-bottle,wood-table)": 0.16782790586876217,
    "on-table(green-bottle,black-table)": 0.0008685769472170554,
    "on-table(green-bottle,white-table)": 0.8339437855174765,
    "on-table(loaf-of-bread,wood-table)": 0.20865788644490144,
    "on-table(loaf-of-bread,black-table)": 0.44632279203506187,
    "on-table(loaf-of-bread,white-table)": 0.04380988681320256,
    "on-table(red-box-of-cereal,wood-table)": 0.46388528573637205,
    "on-table(red-box-of-cereal,black-table)": 0.8096797416607538,
    "on-table(red-box-of-cereal,white-table)": 0.010815587258548476,
    "on-table(red-can-of-soda,wood-table)": 0.8351123780012131,
    "on-table(red-can-of-soda,black-table)": 0.329249618647206,
    "on-table(red-can-of-soda,white-table)": 0.0060038385004948696,
    "robot-gripper-empty()": 0.7496726835767428,
    "robot-gripping(milk-carton)": 0.40142563606301945,
    "robot-gripping(lemon)": 0.09879845970620711,
    "robot-gripping(green-bottle)": 0.018410678021609783,
    "robot-gripping(loaf-of-bread)": 0.2409825281550487,
    "robot-gripping(red-box-of-cereal)": 0.32824540821214515,
    "robot-gripping(red-can-of-soda)": 0.3573529751350482
}