{
    "on-table(milk-carton,wood-table)": 0.3313157223165035,
    "on-table(milk-carton,black-table)": 0.45887882651004475,
    "on-table(milk-carton,white-table)": 0.01628872264700476,
    "on-table(lemon,wood-table)": 0.18286978951558316,
    "on-table(lemon,black-table)": 0.028022188113936863,
    "on-table(lemon,white-table)": 0.8372094643612703,
    "on-table(green-bottle,wood-table)": 0.1634339248072744,
    "on-table(green-bottle,black-table)": 0.0011555991225880764,
    "on-table(green-bottle,white-table)": 0.8368514468893409,
    "on-table(loaf-of-bread,wood-table)": 0.3940938402277728,
    "on-table(loaf-of-bread,black-table)": 0.7442208255330721,
    "on-table(loaf-of-bread,white-table)": 0.02415232060836085,
    "on-table(red-box-of-cereal,wood-table)": 0.12936651660614493,
    "on-table(red-box-of-cereal,black-table)": 0.39131581007192534,
    "on-table(red-box-of-cereal,white-table)": 0.00652321442127383,
    "on-table(red-can-of-soda,wood-table)": 0.08092842498687484,
    "on-table(red-can-of-soda,black-table)": 0.8376457753280798,
    "on-table(red-can-of-soda,white-table)": 0.0011311634818108967,
    "robot-gripper-empty()": 0.6705386957619339,
    "robot-gripping(milk-carton)": 0.5725450403988361,
    "robot-gripping(lemon)": 0.07814811484422535,
    "robot-gripping(green-bottle)": 0.018445265479385853,
    "robot-gripping(loaf-of-bread)": 0.19917466460416713,
    "robot-gripping(red-box-of-cereal)": 0.4825982380037506,
    "robot-gripping(red-can-of-soda)": 0.6529433572043976
}